cctm/__init__.py
cctm/config.py
cctm/exceptions.py
cctm/github.py
cctm/json.py
cctm/path.py
cctm/management/__init__.py
cctm/management/alias.py
cctm/management/fetching.py
cctm/management/listing.py
cctm/management/merging.py
cctm/management/removing.py
cctm/schema/alias.json
cctm/schema/package.json
cctm/schema/readme.rst
cctm/services/__init__.py
cctm/services/installer.py
cctm/services/lookup.py
cctm/services/resolver.py
cctm/services/store.py
cctm/services/wrapper.py
cctm-0.2.dist-info/DESCRIPTION.rst
cctm-0.2.dist-info/entry_points.txt
cctm-0.2.dist-info/METADATA
cctm-0.2.dist-info/metadata.json
cctm-0.2.dist-info/RECORD
cctm-0.2.dist-info/top_level.txt
cctm-0.2.dist-info/WHEEL
