Metadata-Version: 2.0
Name: cctm
Version: 0.2
Summary: cookie cutter template manager
Home-page: https://github.com/podhmo/cctm
Author: podhmo
Author-email: ababjam61@gmail.com
License: mit
Platform: UNKNOWN
Classifier: Programming Language :: Python
Classifier: Programming Language :: Python :: Implementation :: CPython
Requires-Dist: dictremapper
Requires-Dist: handofcats
Requires-Dist: miniconfig
Requires-Dist: miniconfig-argparse
Requires-Dist: cached-property
Requires-Dist: requests
Requires-Dist: cookiecutter
Provides-Extra: docs
Provides-Extra: testing
